iql/__init__.py
iql/_version.py
iql/constants.py
iql/options_parser.py
iql/ql.py
iql/utils.py
iql/datamodel/__init__.py
iql/datamodel/cache.py
iql/datamodel/database.py
iql/datamodel/extension.py
iql/datamodel/querycontainer.py
iql/datamodel/result.py
iql/datamodel/subquery.py
iql/db_connectors/__init__.py
iql/db_connectors/duckdb_connector.py
iql/extensions/__init__.py
iql/extensions/azure_blob_extension.py
iql/extensions/cache_extension.py
iql/extensions/nest_extension.py
iql/extensions/openai_extension.py
iql/extensions/pandas_extension.py
iql/extensions/blpapi_ext/README.txt
iql/extensions/blpapi_ext/__init__.py
iql/extensions/blpapi_ext/blp_api_lowlevel.py
iql/extensions/blpapi_ext/blp_extension.py
iql/extensions/bql_ext/__init__.py
iql/extensions/bql_ext/bql_datamodel.py
iql/extensions/bql_ext/bql_extension.py
iql/extensions/bql_ext/bql_service.py
iql/extensions/bql_ext/bql_wrapper.py
iql/extensions/sqlserver/sqlserver_extension_pymssql.py
iql/extensions/sqlserver/sqlserver_extension_pyodbc.py
iql/jupyter_magics/__init__.py
iql/jupyter_magics/autocomplete_settings.py
iql/jupyter_magics/autocompletion_v2.py
iql/jupyter_magics/iql_magic.py
iql/jupyter_magics/iql_magic_ext.py
iql-1.8.44.dist-info/METADATA
iql-1.8.44.dist-info/WHEEL
iql-1.8.44.dist-info/licenses/LICENSE
iql-1.8.44.dist-info/RECORD
