Metadata-Version: 2.4
Name: IQL
Version: 1.8.44
Summary: I* Query Language
Project-URL: Homepage, https://github.com/iqmo-org/iql
Project-URL: Repository, https://github.com/iqmo-org/iql
Project-URL: Issues, https://github.com/iqmo-org/iql/issues
Author-email: Paul T <paul@iqmo.com>
Maintainer-email: Paul T <paul@iqmo.com>
License-Expression: BSD-3-Clause
License-File: LICENSE
Keywords: blpapi,bql,duckdb,iql,query language
Requires-Python: >=3.11
Requires-Dist: cachetools>=6.1.0
Requires-Dist: duckdb>=1.2.2
Requires-Dist: sqlparse>=0.5.3
